commands/__init__.py
commands/ai.py
commands/game.py
commands/init.py
commands/login.py
commands/logout.py
saiblo_dev_tools/__init__.py
templates/__init__.py
templates/config.py
templates/database.py
utils/__init__.py
utils/config.py
utils/error.py
utils/path.py
utils/storage.py
saiblo_dev_tools-0.0.2.dist-info/LICENSE
saiblo_dev_tools-0.0.2.dist-info/METADATA
saiblo_dev_tools-0.0.2.dist-info/WHEEL
saiblo_dev_tools-0.0.2.dist-info/entry_points.txt
saiblo_dev_tools-0.0.2.dist-info/top_level.txt
saiblo_dev_tools-0.0.2.dist-info/RECORD
