Metadata-Version: 2.1
Name: saiblo-dev-tools
Version: 0.0.2
Summary: Saiblo 游戏开发人员脚本工具
Home-page: https://github.com/saiblo/saiblo-dev-tools
Author: BillXWB
Author-email: 1370302499@qq.com
License: UNKNOWN
Platform: UNKNOWN
Classifier: Programming Language :: Python :: 3
Classifier: License :: OSI Approved :: MIT License
Classifier: Operating System :: OS Independent
License-File: LICENSE
Requires-Dist: requests
